ylogger/__init__.py
ylogger-1.2.dist-info/METADATA
ylogger-1.2.dist-info/WHEEL
ylogger-1.2.dist-info/top_level.txt
ylogger-1.2.dist-info/RECORD
