Metadata-Version: 2.1
Name: ylogger
Version: 1.2
Summary: a logger, see https://github.com/xxmawhu/zlogger
Home-page: UNKNOWN
Author: Z-Z Ma
License: GPL
Project-URL: Source, https://github.com/xxmawhu/zlogger
Platform: UNKNOWN
